angle_view/__init__.py
angle_view/angle_view.py
AngleView-0.0.0.dev1.dist-info/LICENSE
AngleView-0.0.0.dev1.dist-info/METADATA
AngleView-0.0.0.dev1.dist-info/WHEEL
AngleView-0.0.0.dev1.dist-info/top_level.txt
AngleView-0.0.0.dev1.dist-info/RECORD
