Metadata-Version: 2.1
Name: AngleView
Version: 0.0.0.dev1
Summary: Convert JSON to PDF
Home-page: https://github.com/Magani-Stack/AngleView
Author: Abimanyu H K
Author-email: manyu1994@hotmail.com
License: MIT License : Copyright (c) 2020 Magani-Stack
Platform: UNKNOWN
Requires-Dist: reportlab (==3.5.42)
